Smurf/__init__.py
Smurf/assim/__init__.py
Smurf/assim/assim.py
Smurf/assim/ens_kalman_filter.py
Smurf/assim/instanciate.py
Smurf/assim/perturbation.py
Smurf/common/__init__.py
Smurf/common/errors.py
Smurf/common/functions.py
Smurf/common/matrix.py
Smurf/common/vector.py
Smurf/covariances/__init__.py
Smurf/covariances/bkg_cov.py
Smurf/covariances/obs_cov.py
Smurf/experiments/__init__.py
Smurf/experiments/experiment.py
Smurf/models/__init__.py
Smurf/models/barbatruc.py
Smurf/models/instanciate.py
Smurf/models/mascaret.py
Smurf/models/model.py
Smurf/observations/__init__.py
Smurf/observations/barbametre.py
Smurf/observations/events.py
Smurf/observations/gauge.py
Smurf/observations/instanciate.py
Smurf/observations/instrument.py
Smurf/observations/obs_vector.py
Smurf/postprocessing/__init__.py
Smurf/postprocessing/postprocessing.py
Smurf_CERFACS-1.0.1.dist-info/LICENSE
Smurf_CERFACS-1.0.1.dist-info/METADATA
Smurf_CERFACS-1.0.1.dist-info/WHEEL
Smurf_CERFACS-1.0.1.dist-info/top_level.txt
Smurf_CERFACS-1.0.1.dist-info/RECORD
