Metadata-Version: 2.1
Name: Smurf-CERFACS
Version: 1.0.1
Summary: Smurf: System for Modelling with Uncertainty Reduction, and Forecasting
Home-page: https://gitlab.com/cerfacs/Smurf
Author: Isabelle Mirouze
Author-email: isabelle.mirouze@cerfacs.fr
License: CeCILL-B FREE SOFTWARE LICENSE AGREEMENT
Requires-Dist: numpy (>=1.15)
Requires-Dist: pathos (>=0.2)
Requires-Dist: matplotlib (>=3.0)
Requires-Dist: pyyaml (>=3.12)
Requires-Dist: ot-batman (>=1.9)
Requires-Dist: barbatruc (==0.0.2)
